Voting Machine.srcs/sources_1/new/design.sv
`timescale 1ns / 1ps

// Module to handle button press and debounce logic
module buttonControl(
    input clock, reset, button,
    output reg valid_vote
);
    reg [30:0] counter;

    always @(posedge clock) begin
        if (reset)
            counter <= 0;
        else begin
            if (button & counter < 11)
                counter <= counter + 1;
            else if (!button)
                counter <= 0;
        end
    end   

    always @(posedge clock) begin
        if (reset)
            valid_vote <= 1'b0;
        else begin
            if (counter == 10)
                valid_vote <= 1'b1;
            else
                valid_vote <= 1'b0;
        end
    end
endmodule

// Module to log the votes for each candidate
module voteLogger(
    input clock, reset, mode,
    input cand1_vote_valid, cand2_vote_valid, cand3_vote_valid, cand4_vote_valid,
    output reg [7:0] cand1_vote_recvd,
    output reg [7:0] cand2_vote_recvd,
    output reg [7:0] cand3_vote_recvd,
    output reg [7:0] cand4_vote_recvd
);
    always @(posedge clock) begin
        if (reset) begin
            cand1_vote_recvd <= 0;
            cand2_vote_recvd <= 0;
            cand3_vote_recvd <= 0;
            cand4_vote_recvd <= 0;
        end
        else begin
            if (cand1_vote_valid & (mode == 0))
                cand1_vote_recvd <= cand1_vote_recvd + 1;
            else if (cand2_vote_valid & (mode == 0))
                cand2_vote_recvd <= cand2_vote_recvd + 1;
            else if (cand3_vote_valid & (mode == 0))
                cand3_vote_recvd <= cand3_vote_recvd + 1;
            else if (cand4_vote_valid & (mode == 0))
                cand4_vote_recvd <= cand4_vote_recvd + 1;
        end
    end
endmodule

// Module to control display logic and LED output
module modeControl(
    input clock, reset, mode, valid_vote_casted,
    input [7:0] candidate1_vote, candidate2_vote, candidate3_vote, candidate4_vote,
    input candidate1_button_press, candidate2_button_press, candidate3_button_press, candidate4_button_press,
    output reg [7:0] leds
);
    reg [30:0] counter;

    always @(posedge clock) begin
        if (reset)
            counter <= 0;
        else if (valid_vote_casted | (counter != 0 & counter < 10))
            counter <= counter + 1;
        else
            counter <= 0;
    end

    always @(posedge clock) begin 
        if (reset)
            leds <= 0;
        else begin
            if (mode == 0 & counter > 0)
                leds <= 8'hFF;
            else if (mode == 0)
                leds <= 8'h00;
            else if (mode == 1) begin
                if (candidate1_button_press)
                    leds <= candidate1_vote;
                else if (candidate2_button_press)
                    leds <= candidate2_vote;
                else if (candidate3_button_press)
                    leds <= candidate3_vote;
                else if (candidate4_button_press)
                    leds <= candidate4_vote;
                else
                    leds <= 0;
            end
        end
    end
endmodule

// Top-level module connecting all blocks
module votingMachine(
    input clock, reset, mode, button1, button2, button3, button4,
    output [7:0] led
);
    wire valid_vote_1, valid_vote_2, valid_vote_3, valid_vote_4;
    wire [7:0] cand1_vote_recvd, cand2_vote_recvd, cand3_vote_recvd, cand4_vote_recvd;
    wire anyValidVote;

    assign anyValidVote = valid_vote_1 | valid_vote_2 | valid_vote_3 | valid_vote_4;

    buttonControl bc1(clock, reset, button1, valid_vote_1);
    buttonControl bc2(clock, reset, button2, valid_vote_2);
    buttonControl bc3(clock, reset, button3, valid_vote_3);
    buttonControl bc4(clock, reset, button4, valid_vote_4);

    voteLogger VL(
        clock, reset, mode,
        valid_vote_1, valid_vote_2, valid_vote_3, valid_vote_4,
        cand1_vote_recvd, cand2_vote_recvd, cand3_vote_recvd, cand4_vote_recvd
    );

    modeControl MC(
        clock, reset, mode, anyValidVote,
        cand1_vote_recvd, cand2_vote_recvd, cand3_vote_recvd, cand4_vote_recvd,
        button1, button2, button3, button4,
        led
    );
endmodule

Voting Machine.srcs/sim_1/new/testbench.sv
`timescale 1ns / 1ps

module test;

// Declare signals to drive the DUT
reg clock, reset, mode;
reg button1, button2, button3, button4;
wire [7:0] led;

// Instantiate the votingMachine module
votingMachine uut (
    .clock(clock),
    .reset(reset),
    .mode(mode),
    .button1(button1),
    .button2(button2),
    .button3(button3),
    .button4(button4),
    .led(led)
);

// Clock generation
initial begin
    clock = 0;
    forever #5 clock = ~clock;
end

// Test sequence
initial begin
    reset = 1;
    mode = 0;
    button1 = 0; button2 = 0; button3 = 0; button4 = 0;
    #100;
    
    reset = 0;
    mode = 0;
    button1 = 1; #10;
    button1 = 0; #5;
    
    button1 = 1; #10;
    button1 = 0; #200;
    
    button2 = 1; #10;
    button2 = 0; #200;
    
    button2 = 1; button3 = 1; #10;
    button2 = 0; button3 = 0; #200;
    
    mode = 1;
    button1 = 1; button2 = 1; #10;
    button1 = 0; button2 = 0; #200;
    
    button3 = 1; #10;
    button3 = 0; #200;
    
    button1 = 1; button3 = 1; #10;
    button1 = 0; button3 = 0; #200;
end

// Waveform dumping for simulation
initial begin
    $dumpfile("dump.vcd");
    $dumpvars(0, test);
end

endmodule

Voting Machine.sim/sim_1/behav/xsim/dump.vcd
$date
   Sun May 25 18:57:54 2025
$end
$version
  2019.1
$end
$timescale
  1ps
$end
$scope module test $end
$var reg 1 ! clock $end
$var reg 1 " reset $end
$var reg 1 # mode $end
$var reg 1 $ button1 $end
$var reg 1 % button2 $end
$var reg 1 & button3 $end
$var reg 1 ' button4 $end
$var wire 8 ( led [7:0] $end
$scope module uut $end
$var wire 1 ) clock $end
$var wire 1 * reset $end
$var wire 1 + mode $end
$var wire 1 , button1 $end
$var wire 1 - button2 $end
$var wire 1 . button3 $end
$var wire 1 / button4 $end
$var wire 8 ( led [7:0] $end
$var wire 1 0 valid_vote_1 $end
$var wire 1 1 valid_vote_2 $end
$var wire 1 2 valid_vote_3 $end
$var wire 1 3 valid_vote_4 $end
$var wire 8 4 cand1_vote_recvd [7:0] $end
$var wire 8 5 cand2_vote_recvd [7:0] $end
$var wire 8 6 cand3_vote_recvd [7:0] $end
$var wire 8 7 cand4_vote_recvd [7:0] $end
$var wire 1 8 anyValidVote $end
$scope module bc1 $end
$var wire 1 ) clock $end
$var wire 1 * reset $end
$var wire 1 , button $end
$var reg 1 9 valid_vote $end
$var reg 31 : counter [30:0] $end
$upscope $end
$scope module bc2 $end
$var wire 1 ) clock $end
$var wire 1 * reset $end
$var wire 1 - button $end
$var reg 1 ; valid_vote $end
$var reg 31 < counter [30:0] $end
$upscope $end
$scope module bc3 $end
$var wire 1 ) clock $end
$var wire 1 * reset $end
$var wire 1 . button $end
$var reg 1 = valid_vote $end
$var reg 31 > counter [30:0] $end
$upscope $end
$scope module bc4 $end
$var wire 1 ) clock $end
$var wire 1 * reset $end
$var wire 1 / button $end
$var reg 1 ? valid_vote $end
$var reg 31 @ counter [30:0] $end
$upscope $end
$scope module VL $end
$var wire 1 ) clock $end
$var wire 1 * reset $end
$var wire 1 + mode $end
$var wire 1 0 cand1_vote_valid $end
$var wire 1 1 cand2_vote_valid $end
$var wire 1 2 cand3_vote_valid $end
$var wire 1 3 cand4_vote_valid $end
$var reg 8 A cand1_vote_recvd [7:0] $end
$var reg 8 B cand2_vote_recvd [7:0] $end
$var reg 8 C cand3_vote_recvd [7:0] $end
$var reg 8 D cand4_vote_recvd [7:0] $end
$upscope $end
$scope module MC $end
$var wire 1 ) clock $end
$var wire 1 * reset $end
$var wire 1 + mode $end
$var wire 1 8 valid_vote_casted $end
$var wire 8 4 candidate1_vote [7:0] $end
$var wire 8 5 candidate2_vote [7:0] $end
$var wire 8 6 candidate3_vote [7:0] $end
$var wire 8 7 candidate4_vote [7:0] $end
$var wire 1 , candidate1_button_press $end
$var wire 1 - candidate2_button_press $end
$var wire 1 . candidate3_button_press $end
$var wire 1 / candidate4_button_press $end
$var reg 8 E leds [7:0] $end
$var reg 31 F counter [30:0] $end
$upscope $end
$upscope $end
$upscope $end
$enddefinitions $end
#0
$dumpvars
0!
1"
0#
0$
0%
0&
0'
bx (
0)
1*
0+
0,
0-
0.
0/
x0
x1
x2
x3
bx 4
bx 5
bx 6
bx 7
x8
x9
bx :
x;
bx <
x=
bx >
x?
bx @
bx A
bx B
bx C
bx D
bx E
bx F
$end
#5000
1!
b0 (
1)
00
01
02
03
b0 4
b0 5
b0 6
b0 7
08
09
b0 :
0;
b0 <
0=
b0 >
0?
b0 @
b0 A
b0 B
b0 C
b0 D
b0 E
b0 F
#10000
0!
0)
#15000
1!
1)
#20000
0!
0)
#25000
1!
1)
#30000
0!
0)
#35000
1!
1)
#40000
0!
0)
#45000
1!
1)
#50000
0!
0)
#55000
1!
1)
#60000
0!
0)
#65000
1!
1)
#70000
0!
0)
#75000
1!
1)
#80000
0!
0)
#85000
1!
1)
#90000
0!
0)
#95000
1!
1)
#100000
0!
0"
1$
0)
0*
1,
#105000
1!
1)
b1 :
#110000
0!
0$
0)
0,
#115000
1!
1$
1)
1,
b10 :
#120000
0!
0)
#125000
1!
0$
1)
0,
b0 :
#130000
0!
0)
#135000
1!
1)
#140000
0!
0)
#145000
1!
1)
#150000
0!
0)
#155000
1!
1)
#160000
0!
0)
#165000
1!
1)
#170000
0!
0)
#175000
1!
1)
#180000
0!
0)
#185000
1!
1)
#190000
0!
0)
#195000
1!
1)
#200000
0!
0)
#205000
1!
1)
#210000
0!
0)
#215000
1!
1)
#220000
0!
0)
#225000
1!
1)
#230000
0!
0)
#235000
1!
1)
#240000
0!
0)
#245000
1!
1)
#250000
0!
0)
#255000
1!
1)
#260000
0!
0)
#265000
1!
1)
#270000
0!
0)
#275000
1!
1)
#280000
0!
0)
#285000
1!
1)
#290000
0!
0)
#295000
1!
1)
#300000
0!
0)
#305000
1!
1)
#310000
0!
0)
#315000
1!
1)
#320000
0!
0)
#325000
1!
1%
1)
1-
b1 <
#330000
0!
0)
#335000
1!
0%
1)
0-
b0 <
#340000
0!
0)
#345000
1!
1)
#350000
0!
0)
#355000
1!
1)
#360000
0!
0)
#365000
1!
1)
#370000
0!
0)
#375000
1!
1)
#380000
0!
0)
#385000
1!
1)
#390000
0!
0)
#395000
1!
1)
#400000
0!
0)
#405000
1!
1)
#410000
0!
0)
#415000
1!
1)
#420000
0!
0)
#425000
1!
1)
#430000
0!
0)
#435000
1!
1)
#440000
0!
0)
#445000
1!
1)
#450000
0!
0)
#455000
1!
1)
#460000
0!
0)
#465000
1!
1)
#470000
0!
0)
#475000
1!
1)
#480000
0!
0)
#485000
1!
1)
#490000
0!
0)
#495000
1!
1)
#500000
0!
0)
#505000
1!
1)
#510000
0!
0)
#515000
1!
1)
#520000
0!
0)
#525000
1!
1)
#530000
0!
0)
#535000
1!
1%
1&
1)
1-
1.
b1 <
b1 >
#540000
0!
0)
#545000
1!
0%
0&
1)
0-
0.
b0 <
b0 >
#550000
0!
0)
#555000
1!
1)
#560000
0!
0)
#565000
1!
1)
#570000
0!
0)
#575000
1!
1)
#580000
0!
0)
#585000
1!
1)
#590000
0!
0)
#595000
1!
1)
#600000
0!
0)
#605000
1!
1)
#610000
0!
0)
#615000
1!
1)
#620000
0!
0)
#625000
1!
1)
#630000
0!
0)
#635000
1!
1)
#640000
0!
0)
#645000
1!
1)
#650000
0!
0)
#655000
1!
1)
#660000
0!
0)
#665000
1!
1)
#670000
0!
0)
#675000
1!
1)
#680000
0!
0)
#685000
1!
1)
#690000
0!
0)
#695000
1!
1)
#700000
0!
0)
#705000
1!
1)
#710000
0!
0)
#715000
1!
1)
#720000
0!
0)
#725000
1!
1)
#730000
0!
0)
#735000
1!
1)
#740000
0!
0)
#745000
1!
1#
1$
1%
1)
1+
1,
1-
b1 :
b1 <
#750000
0!
0)
#755000
1!
0$
0%
1)
0,
0-
b0 :
b0 <
#760000
0!
0)
#765000
1!
1)
#770000
0!
0)
#775000
1!
1)
#780000
0!
0)
#785000
1!
1)
#790000
0!
0)
#795000
1!
1)
#800000
0!
0)
#805000
1!
1)
#810000
0!
0)
#815000
1!
1)
#820000
0!
0)
#825000
1!
1)
#830000
0!
0)
#835000
1!
1)
#840000
0!
0)
#845000
1!
1)
#850000
0!
0)
#855000
1!
1)
#860000
0!
0)
#865000
1!
1)
#870000
0!
0)
#875000
1!
1)
#880000
0!
0)
#885000
1!
1)
#890000
0!
0)
#895000
1!
1)
#900000
0!
0)
#905000
1!
1)
#910000
0!
0)
#915000
1!
1)
#920000
0!
0)
#925000
1!
1)
#930000
0!
0)
#935000
1!
1)
#940000
0!
0)
#945000
1!
1)
#950000
0!
0)
#955000
1!
1&
1)
1.
b1 >
#960000
0!
0)
#965000
1!
0&
1)
0.
b0 >
